{
	"info": {
		"_postman_id": "083486d6-4302-42f1-941e-51b468bab0b3",
		"name": "pays",
		"schema": "https://schema.getpostman.com/json/collection/v2.1.0/collection.json",
		"_exporter_id": "34961447"
	},
	"item": [
		{
			"name": "404",
			"event": [
				{
					"listen": "test",
					"script": {
						"exec": [
							""
						],
						"type": "text/javascript",
						"packages": {},
						"requests": {}
					}
				}
			],
			"request": {
				"method": "GET",
				"header": [],
				"url": {
					"raw": "{{baseUrl}}",
					"host": [
						"{{baseUrl}}"
					]
				}
			},
			"response": []
		},
		{
			"name": "user_auth_fail",
			"event": [
				{
					"listen": "test",
					"script": {
						"exec": [
							""
						],
						"type": "text/javascript",
						"packages": {},
						"requests": {}
					}
				}
			],
			"protocolProfileBehavior": {
				"disableCookies": true
			},
			"request": {
				"method": "GET",
				"header": [],
				"url": {
					"raw": "{{user1Auth}}/my-profile",
					"host": [
						"{{user1Auth}}"
					],
					"path": [
						"my-profile"
					]
				}
			},
			"response": []
		},
		{
			"name": "user1_signup_success",
			"event": [
				{
					"listen": "test",
					"script": {
						"exec": [
							""
						],
						"type": "text/javascript",
						"packages": {},
						"requests": {}
					}
				}
			],
			"protocolProfileBehavior": {
				"disableCookies": false
			},
			"request": {
				"method": "POST",
				"header": [],
				"body": {
					"mode": "raw",
					"raw": "{\r\n    \"email\" : \"user1@example.com\",\r\n    \"userName\": \"user_one\",\r\n    \"fullName\": \"User one\",\r\n    \"password\": \"12345678\"\r\n}",
					"options": {
						"raw": {
							"language": "json"
						}
					}
				},
				"url": {
					"raw": "{{user1Auth}}/signup",
					"host": [
						"{{user1Auth}}"
					],
					"path": [
						"signup"
					]
				}
			},
			"response": []
		},
		{
			"name": "user_signup_duplicate_fail",
			"request": {
				"method": "POST",
				"header": [],
				"body": {
					"mode": "raw",
					"raw": "{\r\n    \"email\" : \"user1@example.com\",\r\n    \"userName\": \"user_one\",\r\n    \"fullName\": \"User one\",\r\n    \"password\": \"12345678\"\r\n}",
					"options": {
						"raw": {
							"language": "json"
						}
					}
				},
				"url": {
					"raw": "{{user1Auth}}/signup",
					"host": [
						"{{user1Auth}}"
					],
					"path": [
						"signup"
					]
				}
			},
			"response": []
		},
		{
			"name": "user2_signup_success",
			"request": {
				"method": "POST",
				"header": [],
				"body": {
					"mode": "raw",
					"raw": "{\r\n    \"email\": \"user2@example.com\",\r\n    \"userName\": \"user_two\",\r\n    \"fullName\": \"User two\",\r\n    \"password\": \"abcdefgh\"\r\n}",
					"options": {
						"raw": {
							"language": "json"
						}
					}
				},
				"url": {
					"raw": "{{user2Auth}}/signup",
					"host": [
						"{{user2Auth}}"
					],
					"path": [
						"signup"
					]
				}
			},
			"response": []
		},
		{
			"name": "user1_login_success",
			"request": {
				"method": "POST",
				"header": [],
				"body": {
					"mode": "raw",
					"raw": "{\r\n    \"email\":\"user1@example.com\",\r\n    \"password\":\"12345678\"\r\n}",
					"options": {
						"raw": {
							"language": "json"
						}
					}
				},
				"url": {
					"raw": "{{user1Auth}}/login",
					"host": [
						"{{user1Auth}}"
					],
					"path": [
						"login"
					]
				}
			},
			"response": []
		},
		{
			"name": "user2_login_success",
			"request": {
				"method": "POST",
				"header": [],
				"body": {
					"mode": "raw",
					"raw": "{\r\n    \"email\":\"user2@example.com\",\r\n    \"password\":\"abcdefgh\"\r\n}",
					"options": {
						"raw": {
							"language": "json"
						}
					}
				},
				"url": {
					"raw": "{{user2Auth}}/login",
					"host": [
						"{{user2Auth}}"
					],
					"path": [
						"login"
					]
				}
			},
			"response": []
		},
		{
			"name": "user1_password_change_success",
			"request": {
				"method": "POST",
				"header": [],
				"body": {
					"mode": "raw",
					"raw": "{\r\n    \"oldPassword\":\"12345678\",\r\n    \"newPassword\":\"abcdefgh\"\r\n}",
					"options": {
						"raw": {
							"language": "json"
						}
					}
				},
				"url": {
					"raw": "{{user1Auth}}/password",
					"host": [
						"{{user1Auth}}"
					],
					"path": [
						"password"
					]
				}
			},
			"response": []
		},
		{
			"name": "user1_password_change_fail",
			"request": {
				"method": "POST",
				"header": [],
				"body": {
					"mode": "raw",
					"raw": "{\r\n    \"oldPassword\" : \"12345678\",\r\n    \"newPassword\" : \"12345678\"\r\n}",
					"options": {
						"raw": {
							"language": "json"
						}
					}
				},
				"url": {
					"raw": "{{user1Auth}}/password",
					"host": [
						"{{user1Auth}}"
					],
					"path": [
						"password"
					]
				}
			},
			"response": []
		},
		{
			"name": "user2_password_change_success",
			"request": {
				"method": "POST",
				"header": [],
				"body": {
					"mode": "raw",
					"raw": "{\r\n    \"oldPassword\" : \"abcdefgh\",\r\n    \"newPassword\" : \"12345678\"\r\n}",
					"options": {
						"raw": {
							"language": "json"
						}
					}
				},
				"url": {
					"raw": "{{user2Auth}}/password",
					"host": [
						"{{user2Auth}}"
					],
					"path": [
						"password"
					]
				}
			},
			"response": []
		},
		{
			"name": "get-current-fullName",
			"request": {
				"method": "POST",
				"header": [],
				"body": {
					"mode": "raw",
					"raw": "{\r\n    \"userName\":\"user_two\"\r\n}",
					"options": {
						"raw": {
							"language": "json"
						}
					}
				},
				"url": {
					"raw": "{{user1}}/get-current-fullname",
					"host": [
						"{{user1}}"
					],
					"path": [
						"get-current-fullname"
					]
				}
			},
			"response": []
		},
		{
			"name": "user1_change_fullName",
			"request": {
				"method": "PATCH",
				"header": [],
				"body": {
					"mode": "raw",
					"raw": "{\r\n    \"fullName\" : \"User one New Name\"\r\n}",
					"options": {
						"raw": {
							"language": "json"
						}
					}
				},
				"url": {
					"raw": "{{user1}}/fullName",
					"host": [
						"{{user1}}"
					],
					"path": [
						"fullName"
					]
				}
			},
			"response": []
		},
		{
			"name": "user2_change_fullName",
			"request": {
				"method": "PATCH",
				"header": [],
				"body": {
					"mode": "raw",
					"raw": "{\r\n    \"fullName\": \"User two New Name\"\r\n}",
					"options": {
						"raw": {
							"language": "json"
						}
					}
				},
				"url": {
					"raw": "{{user2}}/fullName",
					"host": [
						"{{user2}}"
					],
					"path": [
						"fullName"
					]
				}
			},
			"response": []
		},
		{
			"name": "user1_get_users",
			"request": {
				"method": "GET",
				"header": [],
				"url": {
					"raw": "{{user1}}/bulk",
					"host": [
						"{{user1}}"
					],
					"path": [
						"bulk"
					]
				}
			},
			"response": []
		},
		{
			"name": "user1_get_users_with_filter",
			"request": {
				"method": "GET",
				"header": [],
				"url": {
					"raw": "{{user1}}/bulk?filter=user",
					"host": [
						"{{user1}}"
					],
					"path": [
						"bulk"
					],
					"query": [
						{
							"key": "filter",
							"value": "user"
						}
					]
				}
			},
			"response": []
		},
		{
			"name": "user1_get_users_with_filter_invalid_userName",
			"request": {
				"method": "GET",
				"header": [],
				"url": {
					"raw": "{{user1}}/bulk?filter=not-valid-user-name",
					"host": [
						"{{user1}}"
					],
					"path": [
						"bulk"
					],
					"query": [
						{
							"key": "filter",
							"value": "not-valid-user-name"
						}
					]
				}
			},
			"response": []
		},
		{
			"name": "user1Balance",
			"request": {
				"method": "GET",
				"header": [],
				"url": {
					"raw": "{{user1}}/balance",
					"host": [
						"{{user1}}"
					],
					"path": [
						"balance"
					]
				}
			},
			"response": []
		},
		{
			"name": "user2Balance",
			"request": {
				"method": "GET",
				"header": [],
				"url": {
					"raw": "{{user2}}/balance",
					"host": [
						"{{user2}}"
					],
					"path": [
						"balance"
					]
				}
			},
			"response": []
		},
		{
			"name": "user1_pays_to_user2",
			"request": {
				"method": "POST",
				"header": [],
				"body": {
					"mode": "raw",
					"raw": "{\r\n    \"receiverUserName\":\"user_two\",\r\n    \"amountStr\":\"1000\",\r\n    \"description\":\"Payment 1\"\r\n}",
					"options": {
						"raw": {
							"language": "json"
						}
					}
				},
				"url": {
					"raw": "{{user1Pay}}",
					"host": [
						"{{user1Pay}}"
					]
				}
			},
			"response": []
		},
		{
			"name": "user1_pays_to_user2_invalid",
			"request": {
				"method": "POST",
				"header": [],
				"body": {
					"mode": "raw",
					"raw": "{\r\n    \"receiverUserName\":\"user_two\",\r\n    \"amountStr\":\"0\",\r\n    \"description\":\"Payment 2\"\r\n}",
					"options": {
						"raw": {
							"language": "json"
						}
					}
				},
				"url": {
					"raw": "{{user1Pay}}",
					"host": [
						"{{user1Pay}}"
					]
				}
			},
			"response": []
		},
		{
			"name": "user2_pays_to_user1",
			"event": [
				{
					"listen": "test",
					"script": {
						"exec": [
							""
						],
						"type": "text/javascript",
						"packages": {},
						"requests": {}
					}
				}
			],
			"request": {
				"method": "POST",
				"header": [],
				"body": {
					"mode": "raw",
					"raw": "{\r\n      \"receiverUserName\": \"user_one\",\r\n      \"amountStr\": \"100\"\r\n}",
					"options": {
						"raw": {
							"language": "json"
						}
					}
				},
				"url": {
					"raw": "{{user2Pay}}",
					"host": [
						"{{user2Pay}}"
					]
				}
			},
			"response": []
		},
		{
			"name": "pay_to_max_balance_fail",
			"request": {
				"method": "POST",
				"header": [],
				"body": {
					"mode": "raw",
					"raw": "{\r\n      \"receiverUserName\": \"max_balance\",\r\n      \"amountStr\": \"1\"\r\n}",
					"options": {
						"raw": {
							"language": "json"
						}
					}
				},
				"url": {
					"raw": "{{user1Pay}}",
					"host": [
						"{{user1Pay}}"
					]
				}
			},
			"response": []
		},
		{
			"name": "user1_payments_history",
			"request": {
				"method": "GET",
				"header": [],
				"url": {
					"raw": "{{user1Pay}}",
					"host": [
						"{{user1Pay}}"
					]
				}
			},
			"response": []
		},
		{
			"name": "user2_payments_history",
			"request": {
				"method": "GET",
				"header": [],
				"url": {
					"raw": "{{user2Pay}}?type=sent",
					"host": [
						"{{user2Pay}}"
					],
					"query": [
						{
							"key": "type",
							"value": "sent"
						},
						{
							"key": "sort",
							"value": "asc",
							"disabled": true
						},
						{
							"key": "page",
							"value": "1",
							"disabled": true
						},
						{
							"key": "limit",
							"value": "2",
							"disabled": true
						}
					]
				}
			},
			"response": []
		},
		{
			"name": "user1_logout",
			"request": {
				"method": "POST",
				"header": [],
				"url": {
					"raw": "{{user1Auth}}/logout",
					"host": [
						"{{user1Auth}}"
					],
					"path": [
						"logout"
					]
				}
			},
			"response": []
		},
		{
			"name": "user2_logout",
			"request": {
				"method": "POST",
				"header": [],
				"url": {
					"raw": "{{user2Auth}}/logout",
					"host": [
						"{{user2Auth}}"
					],
					"path": [
						"logout"
					]
				}
			},
			"response": []
		}
	],
	"event": [
		{
			"listen": "prerequest",
			"script": {
				"type": "text/javascript",
				"packages": {},
				"requests": {},
				"exec": [
					""
				]
			}
		},
		{
			"listen": "test",
			"script": {
				"type": "text/javascript",
				"packages": {},
				"requests": {},
				"exec": [
					""
				]
			}
		}
	]
}